carson/LICENSE
carson/__init__.py
carson/__main__.py
carson/auth.py
carson/config.py
carson/core.py
carson/endpoints.py
carson/logging.py
carson/stream.py
carson/utils.py
carson/plat/Windows.py
carson/plat/__init__.py
carson/version/__init__.py
cartson-3.3.3.dist-info/METADATA
cartson-3.3.3.dist-info/WHEEL
cartson-3.3.3.dist-info/top_level.txt
cartson-3.3.3.dist-info/RECORD
