Metadata-Version: 2.1
Name: cartson
Version: 3.3.3
Author-email: Michael Loyd <michael@loyd.org>
License: MIT
Project-URL: url, https://github.com/mloyd/carson
Keywords: tesla,asyncio,json
Classifier: Development Status :: 5 - Production/Stable
Classifier: Intended Audience :: Developers
Classifier: Topic :: Software Development :: Libraries
Classifier: Topic :: Software Development :: Libraries :: Python Modules
Classifier: License :: OSI Approved :: MIT License
Classifier: Programming Language :: Python :: 3
Requires-Python: >=3.8
Requires-Dist: aiohttp
